ccnotify/__init__.py
ccnotify/cli.py
ccnotify/config.py
ccnotify/notify.py
ccnotify/setup.py
ccnotify/version.py
ccnotify/installer/__init__.py
ccnotify/installer/detector.py
ccnotify/installer/flows.py
ccnotify/installer/updater.py
ccnotify/installer/welcome.py
ccnotify/tts/__init__.py
ccnotify/tts/base.py
ccnotify/tts/elevenlabs.py
ccnotify/tts/factory.py
ccnotify/tts/kokoro.py
ccnotify-0.1.13.dist-info/METADATA
ccnotify-0.1.13.dist-info/WHEEL
ccnotify-0.1.13.dist-info/entry_points.txt
ccnotify-0.1.13.dist-info/licenses/LICENSE
ccnotify-0.1.13.dist-info/RECORD
