Metadata-Version: 2.4
Name: ccnotify
Version: 0.1.13
Summary: Intelligent notification system for Claude Code with audio feedback
Project-URL: Homepage, https://github.com/Helmi/CCNotify
Project-URL: Repository, https://github.com/Helmi/CCNotify
Project-URL: Issues, https://github.com/Helmi/CCNotify/issues
Project-URL: Documentation, https://github.com/Helmi/CCNotify#readme
Author-email: Frank Helmschrott <frank@helmschrott.de>
License: MIT
License-File: LICENSE
Keywords: audio,claude-code,notifications,productivity,tts
Classifier: Development Status :: 4 - Beta
Classifier: Intended Audience :: Developers
Classifier: License :: OSI Approved :: MIT License
Classifier: Operating System :: MacOS
Classifier: Operating System :: POSIX :: Linux
Classifier: Programming Language :: Python :: 3
Classifier: Programming Language :: Python :: 3 :: Only
Classifier: Topic :: Multimedia :: Sound/Audio :: Speech
Classifier: Topic :: Software Development :: Libraries :: Python Modules
Classifier: Topic :: System :: Monitoring
Requires-Python: >=3.10
Requires-Dist: kokoro-onnx>=0.3.9
Requires-Dist: pathlib2>=2.3.7; python_version < '3.11'
Requires-Dist: plyer>=2.1.0; sys_platform != 'darwin'
Requires-Dist: pydub>=0.25.1
Requires-Dist: pync>=2.0.3; sys_platform == 'darwin'
Requires-Dist: python-dotenv>=1.0.0
Requires-Dist: requests>=2.28.0
Requires-Dist: rich>=13.0.0
Requires-Dist: soundfile>=0.12.1
Requires-Dist: tqdm>=4.64.0
Provides-Extra: dev
Requires-Dist: black>=22.0.0; extra == 'dev'
Requires-Dist: isort>=5.0.0; extra == 'dev'
Requires-Dist: mypy>=1.0.0; extra == 'dev'
Requires-Dist: pre-commit>=3.0.0; extra == 'dev'
Requires-Dist: pytest-cov>=4.0.0; extra == 'dev'
Requires-Dist: pytest>=7.0.0; extra == 'dev'
Provides-Extra: full
Requires-Dist: elevenlabs>=0.2.0; extra == 'full'
